setup.py
console_script/__init__.py
console_script.egg-info/PKG-INFO
console_script.egg-info/SOURCES.txt
console_script.egg-info/dependency_links.txt
console_script.egg-info/entry_points.txt
console_script.egg-info/not-zip-safe
console_script.egg-info/requires.txt
console_script.egg-info/top_level.txt