Metadata-Version: 1.0
Name: console-script
Version: 0.1
Summary: pastescript template for creating command line applications
Home-page: http://k0s.org
Author: Jeff Hammel
Author-email: k0scist@gmail.com
License: UNKNOWN
Keywords: trac plugin
Platform: UNKNOWN
